[{"B": [[8, -7, -5], [-1, 1, 2], [6, -4, -7]], "G": [[138, -25, 111], [-25, 6, -24], [111, -24, 101]], "lincomb_exact": [0.0, 4.0, 1.0], "lincomb_LLL": [0.0, 4.0, 1.0], "lincomb_cube": [-0.32512331008911133, 2.6453208923339844, 1.0], "lincomb_cube_shortest": [0.0, 3.0, 1.0], "exact.norm": 2.2360687255859375, "LLL.norm": 2.2360687255859375, "shortest_cube.norm": 3.3166236877441406, "sv_LLL": [2.0, 0.0, 1.0], "sv_exact": [2.0, 0.0, 1.0], "sv_shortst_cube": [3.0, -1.0, -1.0]}, {"B": [[0, 3, -1], [-2, -5, 1], [6, 8, 1]], "G": [[10, -16, 23], [-16, 30, -51], [23, -51, 101]], "lincomb_exact": [3.0, 3.0, 1.0], "lincomb_LLL": [4.0, 4.0, 1.0], "lincomb_cube": [2.863636016845703, 3.2272720336914062, 1.0], "lincomb_cube_shortest": [2.0, 3.0, 1.0], "exact.norm": 2.2360687255859375, "LLL.norm": 2.2360687255859375, "shortest_cube.norm": 2.2360687255859375, "sv_LLL": [-2.0, 0.0, 1.0], "sv_exact": [0.0, 2.0, 1.0], "sv_shortst_cube": [0.0, -1.0, 2.0]}, {"B": [[-9, 1, 4], [-4, 3, -7], [10, -1, -5]], "G": [[98, 11, -111], [11, 74, -8], [-111, -8, 126]], "lincomb_exact": [-16.0, 1.0, -14.0], "lincomb_LLL": [-16.0, 1.0, -14.0], "lincomb_cube": [-18.4444580078125, 1.0, -16.1851806640625], "lincomb_cube_shortest": [-18.0, 1.0, -16.0], "exact.norm": 1.4142131805419922, "LLL.norm": 1.4142131805419922, "shortest_cube.norm": 2.4494895935058594, "sv_LLL": [0.0, 1.0, -1.0], "sv_exact": [0.0, 1.0, -1.0], "sv_shortst_cube": [-2.0, 1.0, 1.0]}, {"B": [[7, -3, -2], [1, 5, 8], [8, -8, -6]], "G": [[62, -24, 92], [-24, 90, -80], [92, -80, 164]], "lincomb_exact": [-1.0, 1.0, 1.0], "lincomb_LLL": [-1.0, 1.0, 1.0], "lincomb_cube": [-2.009387969970703, 1.0, 1.6150226593017578], "lincomb_cube_shortest": [-3.0, 1.0, 2.0], "exact.norm": 4.472137451171875, "LLL.norm": 4.472137451171875, "shortest_cube.norm": 4.898979187011719, "sv_LLL": [2.0, 0.0, 4.0], "sv_exact": [2.0, 0.0, 4.0], "sv_shortst_cube": [-4.0, -2.0, 2.0]}]